[{"animated":false,"description":"<p>Graphic I created to illustrate the Netlify + Dropbox process described in <a href=\"https://www.netlify.com/blog/2018/10/15/combining-netlify-with-dropbox-for-a-one-click-publishing-process/\" rel=\"nofollow noreferrer\">my guest post on Netlify’s blog</a>. </p>","height":600,"html_url":"https://dribbble.com/shots/5406428-Netlibox","id":5406428,"images":{"hidpi":"https://cdn.dribbble.com/users/44352/screenshots/5406428/netlify-post.png","normal":"https://cdn.dribbble.com/users/44352/screenshots/5406428/netlify-post_1x.png","one_x":"https://cdn.dribbble.com/users/44352/screenshots/5406428/netlify-post_1x.png","two_x":"https://cdn.dribbble.com/users/44352/screenshots/5406428/netlify-post.png","teaser":"https://cdn.dribbble.com/users/44352/screenshots/5406428/netlify-post_teaser.png"},"low_profile":false,"tags":["web","web design"],"title":"Netlibox","width":800,"published_at":"2018-10-16T21:04:36Z","updated_at":"2020-04-23T00:50:34Z","attachments":[],"projects":[],"video":null},{"animated":false,"description":"<p>Working on a new pattern and layout for views where users are unauthenticated (including this one, the login page).</p>","height":600,"html_url":"https://dribbble.com/shots/2843802-App-login","id":2843802,"images":{"hidpi":"https://cdn.dribbble.com/users/44352/screenshots/2843802/groundwork-login.png","normal":"https://cdn.dribbble.com/users/44352/screenshots/2843802/groundwork-login_1x.png","one_x":"https://cdn.dribbble.com/users/44352/screenshots/2843802/groundwork-login_1x.png","two_x":"https://cdn.dribbble.com/users/44352/screenshots/2843802/groundwork-login.png","teaser":"https://cdn.dribbble.com/users/44352/screenshots/2843802/groundwork-login_teaser.png"},"low_profile":false,"tags":["login","material-design","material-ui"],"title":"App login","width":800,"published_at":"2016-07-18T15:13:08Z","updated_at":"2020-04-22T22:15:25Z","attachments":[],"projects":[],"video":null},{"animated":false,"description":"<p>Working on ideas for a 404 page for <a href=\"http://iosicongallery.com\" rel=\"nofollow noreferrer\">iosicongallery.com</a></p>","height":600,"html_url":"https://dribbble.com/shots/4015464-404-page","id":4015464,"images":{"hidpi":"https://cdn.dribbble.com/users/44352/screenshots/4015464/404.png","normal":"https://cdn.dribbble.com/users/44352/screenshots/4015464/404_1x.png","one_x":"https://cdn.dribbble.com/users/44352/screenshots/4015464/404_1x.png","two_x":"https://cdn.dribbble.com/users/44352/screenshots/4015464/404.png","teaser":"https://cdn.dribbble.com/users/44352/screenshots/4015464/404_teaser.png"},"low_profile":false,"tags":["404"],"title":"404 page","width":800,"published_at":"2017-12-12T15:52:37Z","updated_at":"2020-04-22T23:29:38Z","attachments":[],"projects":[],"video":null},{"animated":false,"description":"<p>Building the front-end for this stepper/wizard UI I designed around sending event messages.</p>","height":600,"html_url":"https://dribbble.com/shots/2852050-Step-Wizard","id":2852050,"images":{"hidpi":"https://cdn.dribbble.com/users/44352/screenshots/2852050/stepper.png","normal":"https://cdn.dribbble.com/users/44352/screenshots/2852050/stepper_1x.png","one_x":"https://cdn.dribbble.com/users/44352/screenshots/2852050/stepper_1x.png","two_x":"https://cdn.dribbble.com/users/44352/screenshots/2852050/stepper.png","teaser":"https://cdn.dribbble.com/users/44352/screenshots/2852050/stepper_teaser.png"},"low_profile":false,"tags":["step","stepper","wizard"],"title":"Step Wizard","width":800,"published_at":"2016-07-21T21:27:46Z","updated_at":"2020-04-22T22:15:51Z","attachments":[],"projects":[],"video":null},{"animated":false,"description":"<p>Tried doing a dark version of Morgan's iOS style popover with three states: selected, not selected, and onselect ... you can grab the PSD here: http://cl.ly/2m1X300T2v2w3C1s1G3x</p>","height":300,"html_url":"https://dribbble.com/shots/315913-Popover-Dark","id":315913,"images":{"hidpi":null,"normal":"https://cdn.dribbble.com/users/44352/screenshots/315913/popover.png","one_x":"https://cdn.dribbble.com/users/44352/screenshots/315913/popover_1x.png","teaser":"https://cdn.dribbble.com/users/44352/screenshots/315913/popover_teaser.png"},"low_profile":false,"tags":["download","free"],"title":"Popover (Dark)","width":400,"published_at":"2011-11-10T16:14:59Z","updated_at":"2020-04-21T23:22:19Z","attachments":[],"projects":[],"video":null},{"animated":false,"description":"<p>Playing with some possibilities for an identity mark that plays with dual-meanings</p>","height":600,"html_url":"https://dribbble.com/shots/1166825-Identity-mark","id":1166825,"images":{"hidpi":"https://cdn.dribbble.com/users/44352/screenshots/1166825/current.png","normal":"https://cdn.dribbble.com/users/44352/screenshots/1166825/current_1x.png","one_x":"https://cdn.dribbble.com/users/44352/screenshots/1166825/current_1x.png","two_x":"https://cdn.dribbble.com/users/44352/screenshots/1166825/current.png","teaser":"https://cdn.dribbble.com/users/44352/screenshots/1166825/current_teaser.png"},"low_profile":false,"tags":["brand","logo"],"title":"Identity mark","width":800,"published_at":"2013-07-23T15:35:41Z","updated_at":"2020-04-22T21:01:53Z","attachments":[],"projects":[],"video":null},{"animated":false,"description":null,"height":300,"html_url":"https://dribbble.com/shots/1135620-Responsive-graphic","id":1135620,"images":{"hidpi":null,"normal":"https://cdn.dribbble.com/users/44352/screenshots/1135620/mobile.png","one_x":"https://cdn.dribbble.com/users/44352/screenshots/1135620/mobile_1x.png","teaser":"https://cdn.dribbble.com/users/44352/screenshots/1135620/mobile_teaser.png"},"low_profile":false,"tags":["responsive"],"title":"Responsive graphic","width":400,"published_at":"2013-06-28T22:04:24Z","updated_at":"2020-04-21T23:49:16Z","attachments":[],"projects":[],"video":null},{"animated":false,"description":"<p>Working on a 404 page, trying to keep it simple.</p>","height":600,"html_url":"https://dribbble.com/shots/2292911-404-Error","id":2292911,"images":{"hidpi":"https://cdn.dribbble.com/users/44352/screenshots/2292911/404.png","normal":"https://cdn.dribbble.com/users/44352/screenshots/2292911/404_1x.png","one_x":"https://cdn.dribbble.com/users/44352/screenshots/2292911/404_1x.png","two_x":"https://cdn.dribbble.com/users/44352/screenshots/2292911/404.png","teaser":"https://cdn.dribbble.com/users/44352/screenshots/2292911/404_teaser.png"},"low_profile":false,"tags":[],"title":"404 Error","width":800,"published_at":"2015-10-14T21:29:51Z","updated_at":"2020-04-22T21:48:31Z","attachments":[],"projects":[],"video":null},{"animated":false,"description":"<p>Some stuff I did around a desktop web application's branding work. You can <a href=\"http://jim-nielsen.com/blog/2015/assignment-desk-logo/\" rel=\"nofollow noreferrer\">read more</a> about the process if you want.</p>","height":600,"html_url":"https://dribbble.com/shots/2386067-Application-logo","id":2386067,"images":{"hidpi":"https://cdn.dribbble.com/users/44352/screenshots/2386067/assignment-desk.png","normal":"https://cdn.dribbble.com/users/44352/screenshots/2386067/assignment-desk_1x.png","one_x":"https://cdn.dribbble.com/users/44352/screenshots/2386067/assignment-desk_1x.png","two_x":"https://cdn.dribbble.com/users/44352/screenshots/2386067/assignment-desk.png","teaser":"https://cdn.dribbble.com/users/44352/screenshots/2386067/assignment-desk_teaser.png"},"low_profile":false,"tags":["logo","logo design"],"title":"Application logo","width":800,"published_at":"2015-12-03T15:24:17Z","updated_at":"2020-04-22T21:52:58Z","attachments":[],"projects":[],"video":null},{"animated":false,"description":"<p>Just stuff from an old landing page design that never made it live</p>","height":300,"html_url":"https://dribbble.com/shots/1077573-Landing-Page","id":1077573,"images":{"hidpi":null,"normal":"https://cdn.dribbble.com/users/44352/screenshots/1077573/landing-page.jpg","one_x":"https://cdn.dribbble.com/users/44352/screenshots/1077573/landing-page_1x.jpg","teaser":"https://cdn.dribbble.com/users/44352/screenshots/1077573/landing-page_teaser.jpg"},"low_profile":false,"tags":["landing-page","loupe","screenshot","zoom"],"title":"Landing Page","width":400,"published_at":"2013-05-19T20:45:27Z","updated_at":"2020-04-21T23:47:03Z","attachments":[],"projects":[],"video":null},{"animated":false,"description":"<p>Playing with the design of an apple-touch-icon ... it's reminding me that <a href=\"http://jim-nielsen.com/blog/posts/creating-apple-touch-icons/\" rel=\"nofollow\">subtleties</a> can take you a long way.</p>","height":600,"html_url":"https://dribbble.com/shots/1784873-Apple-Touch-Icon","id":1784873,"images":{"hidpi":"https://cdn.dribbble.com/users/44352/screenshots/1784873/app-icon.jpg","normal":"https://cdn.dribbble.com/users/44352/screenshots/1784873/app-icon_1x.jpg","one_x":"https://cdn.dribbble.com/users/44352/screenshots/1784873/app-icon_1x.jpg","two_x":"https://cdn.dribbble.com/users/44352/screenshots/1784873/app-icon.jpg","teaser":"https://cdn.dribbble.com/users/44352/screenshots/1784873/app-icon_teaser.jpg"},"low_profile":false,"tags":["icon","ios"],"title":"Apple Touch Icon","width":800,"published_at":"2014-10-28T22:10:12Z","updated_at":"2020-04-22T21:25:59Z","attachments":[],"projects":[],"video":null},{"animated":false,"description":"<p>Rebound of <a href=\"http://dribbble.com/shots/342738-Search-Rebound-It-\">Matt Gentile's</a> search. Just wanted to try incorporating the search icon into the type. There's probably a lot you could do with the \"c\" as well...Century Gothic for those curious </p>","height":300,"html_url":"https://dribbble.com/shots/348252-Search","id":348252,"images":{"hidpi":null,"normal":"https://cdn.dribbble.com/users/44352/screenshots/348252/search.png","one_x":"https://cdn.dribbble.com/users/44352/screenshots/348252/search_1x.png","teaser":"https://cdn.dribbble.com/users/44352/screenshots/348252/search_teaser.png"},"low_profile":false,"tags":["search"],"title":"Search","width":400,"published_at":"2011-12-11T00:45:15Z","updated_at":"2020-04-21T23:23:20Z","attachments":[],"projects":[],"video":null},{"animated":false,"description":"<p>Working on a flip clock style design for newsletter.</p>","height":300,"html_url":"https://dribbble.com/shots/1345208-Newsletter-graphic","id":1345208,"images":{"hidpi":null,"normal":"https://cdn.dribbble.com/users/44352/screenshots/1345208/2014.png","one_x":"https://cdn.dribbble.com/users/44352/screenshots/1345208/2014_1x.png","teaser":"https://cdn.dribbble.com/users/44352/screenshots/1345208/2014_teaser.png"},"low_profile":false,"tags":["calendar","counter","orange"],"title":"Newsletter graphic","width":400,"published_at":"2013-12-12T22:52:36Z","updated_at":"2020-04-22T21:08:38Z","attachments":[],"projects":[],"video":null},{"animated":false,"description":null,"height":300,"html_url":"https://dribbble.com/shots/1427079-Brand-Identity-Layout","id":1427079,"images":{"hidpi":null,"normal":"https://cdn.dribbble.com/users/44352/screenshots/1427079/layout.jpg","one_x":"https://cdn.dribbble.com/users/44352/screenshots/1427079/layout_1x.jpg","teaser":"https://cdn.dribbble.com/users/44352/screenshots/1427079/layout_teaser.jpg"},"low_profile":false,"tags":["brand","identity","indesign","layout"],"title":"Brand & Identity Layout ","width":400,"published_at":"2014-02-17T21:02:10Z","updated_at":"2020-04-22T21:11:48Z","attachments":[],"projects":[],"video":null},{"animated":false,"description":null,"height":600,"html_url":"https://dribbble.com/shots/1194998-Tennis-symbol","id":1194998,"images":{"hidpi":"https://cdn.dribbble.com/users/44352/screenshots/1194998/tennis.png","normal":"https://cdn.dribbble.com/users/44352/screenshots/1194998/tennis_1x.png","one_x":"https://cdn.dribbble.com/users/44352/screenshots/1194998/tennis_1x.png","two_x":"https://cdn.dribbble.com/users/44352/screenshots/1194998/tennis.png","teaser":"https://cdn.dribbble.com/users/44352/screenshots/1194998/tennis_teaser.png"},"low_profile":false,"tags":[],"title":"Tennis symbol","width":800,"published_at":"2013-08-13T19:57:10Z","updated_at":"2020-04-22T21:02:54Z","attachments":[],"projects":[],"video":null}]