[{"media_type":"CAROUSEL_ALBUM","media_url":"https://scontent-lax3-2.cdninstagram.com/v/t51.29350-15/120199828_207931304083435_4437339096052693652_n.jpg?_nc_cat=107&ccb=2&_nc_sid=8ae9d6&_nc_ohc=6fjlt8UFH84AX_naP-c&_nc_ht=scontent-lax3-2.cdninstagram.com&oh=6bc4e3bd4ba92028406203396a5c994f&oe=5FCC5E46","permalink":"https://www.instagram.com/p/CFrn5fpFemu/","id":"18164551237040211"},{"media_type":"CAROUSEL_ALBUM","media_url":"https://scontent-lax3-2.cdninstagram.com/v/t51.29350-15/110324474_2706789466273694_7161137699856967697_n.jpg?_nc_cat=106&ccb=2&_nc_sid=8ae9d6&_nc_ohc=fLL6b9_YbbIAX9W1MdC&_nc_ht=scontent-lax3-2.cdninstagram.com&oh=d4ca84fb68c076e585b61d37ff40a937&oe=5FCAEAB0","permalink":"https://www.instagram.com/p/CDFvlJtFXxg/","id":"17896922533538523"},{"media_type":"IMAGE","media_url":"https://scontent-lax3-1.cdninstagram.com/v/t51.29350-15/114214886_920269071787983_3754603998913914592_n.jpg?_nc_cat=108&ccb=2&_nc_sid=8ae9d6&_nc_ohc=N44f3ohOYGkAX_nXcDt&_nc_ht=scontent-lax3-1.cdninstagram.com&oh=5fb79016f89bcaf401e972cec4216c96&oe=5FCB8F99","permalink":"https://www.instagram.com/p/CC8q_7rlvHV/","id":"17844926708280516"},{"media_type":"IMAGE","media_url":"https://scontent-lax3-1.cdninstagram.com/v/t51.29350-15/109835044_596832160976537_1449997937212127020_n.jpg?_nc_cat=103&ccb=2&_nc_sid=8ae9d6&_nc_ohc=EwfUy9wLJSsAX9Fk4Up&_nc_ht=scontent-lax3-1.cdninstagram.com&oh=1e21e92055c3191bf7b8ce7ba7bf5cb9&oe=5FCBA030","permalink":"https://www.instagram.com/p/CC6e1j1lM8r/","id":"17852390987132189"},{"media_type":"IMAGE","media_url":"https://scontent-lax3-1.cdninstagram.com/v/t51.2885-15/78794214_112722350222874_8472477359096868899_n.jpg?_nc_cat=103&ccb=2&_nc_sid=8ae9d6&_nc_ohc=13hoAZv0nyAAX8oPe4g&_nc_ht=scontent-lax3-1.cdninstagram.com&oh=bf44c6c08be6f3ca2b6824290f80a054&oe=5FCBCAE2","permalink":"https://www.instagram.com/p/B6I5mMvhJXg/","id":"18113087761070333"},{"media_type":"IMAGE","media_url":"https://scontent-lax3-1.cdninstagram.com/v/t51.2885-15/71219905_437084230316725_8165590266750248197_n.jpg?_nc_cat=108&ccb=2&_nc_sid=8ae9d6&_nc_ohc=JtCOThk1tNcAX9SQBpK&_nc_ht=scontent-lax3-1.cdninstagram.com&oh=e4e33de262088de7a00409abae9763d6&oe=5FCC5650","permalink":"https://www.instagram.com/p/B5b7rZfh3Yt/","id":"17907087808378819"},{"media_type":"CAROUSEL_ALBUM","media_url":"https://scontent-lax3-1.cdninstagram.com/v/t51.2885-15/75225517_2578072115640149_5552644618733164819_n.jpg?_nc_cat=104&ccb=2&_nc_sid=8ae9d6&_nc_ohc=p94J4ooogXkAX8LH4-I&_nc_ht=scontent-lax3-1.cdninstagram.com&oh=2d081df01f92de30c4b8442f6516fcc5&oe=5FCD2122","permalink":"https://www.instagram.com/p/B4qywCdBzGA/","id":"18112974589060645"},{"media_type":"IMAGE","media_url":"https://scontent-lax3-2.cdninstagram.com/v/t51.2885-15/73095011_2417212411894950_2781154776552946564_n.jpg?_nc_cat=111&ccb=2&_nc_sid=8ae9d6&_nc_ohc=vUGecBZdtdsAX_r7teb&_nc_ht=scontent-lax3-2.cdninstagram.com&oh=db748d92b357cdb7bf22710383cb6e29&oe=5FCD13E5","permalink":"https://www.instagram.com/p/B32uA6bhcHs/","id":"17848975579656383"},{"media_type":"CAROUSEL_ALBUM","media_url":"https://scontent-lax3-1.cdninstagram.com/v/t51.2885-15/62229313_112628883153396_378267307310249586_n.jpg?_nc_cat=100&ccb=2&_nc_sid=8ae9d6&_nc_ohc=jH5l1yjkhIsAX9HCgc4&_nc_ht=scontent-lax3-1.cdninstagram.com&oh=2bec0ebbeea97b2893e7f900df44a903&oe=5FCB505B","permalink":"https://www.instagram.com/p/ByyiySZB3db/","id":"18076117570009064"},{"media_type":"CAROUSEL_ALBUM","media_url":"https://scontent-lax3-1.cdninstagram.com/v/t51.2885-15/61196432_118404732726154_8683347078063892889_n.jpg?_nc_cat=100&ccb=2&_nc_sid=8ae9d6&_nc_ohc=0Ev4EQaFwWIAX8soM9a&_nc_ht=scontent-lax3-1.cdninstagram.com&oh=b77cb90a53eafcdb7d783bafac5f0d9a&oe=5FCBE803","permalink":"https://www.instagram.com/p/ByksF4ghCFe/","id":"17872590466375775"},{"media_type":"CAROUSEL_ALBUM","media_url":"https://scontent-lax3-2.cdninstagram.com/v/t51.2885-15/59944100_1047799418739300_883587045977887379_n.jpg?_nc_cat=106&ccb=2&_nc_sid=8ae9d6&_nc_ohc=J7z_ZCYUySIAX8lbrPE&_nc_ht=scontent-lax3-2.cdninstagram.com&oh=89f3b9ea4e308d6049aec415ca23612a&oe=5FCCE9D5","permalink":"https://www.instagram.com/p/Bx98uUWBqoL/","id":"17848268740448933"},{"media_type":"IMAGE","media_url":"https://scontent-lax3-1.cdninstagram.com/v/t51.2885-15/59497840_2335068593405824_3752080472149651479_n.jpg?_nc_cat=103&ccb=2&_nc_sid=8ae9d6&_nc_ohc=iD1jXdbkvwQAX9CHWxX&_nc_ht=scontent-lax3-1.cdninstagram.com&oh=66b8c291982db9d8ad6d0291b3f57530&oe=5FCA6631","permalink":"https://www.instagram.com/p/BxJJm9gBfGU/","id":"18047045593100783"},{"media_type":"IMAGE","media_url":"https://scontent-lax3-1.cdninstagram.com/v/t51.2885-15/56616343_386872148574999_7966330204857405595_n.jpg?_nc_cat=109&ccb=2&_nc_sid=8ae9d6&_nc_ohc=gpN72R5H4LwAX8sa7pm&_nc_ht=scontent-lax3-1.cdninstagram.com&oh=a1695d40a385cda7aad89959acd669a3&oe=5FCB89AA","permalink":"https://www.instagram.com/p/Bwikhphh_2K/","id":"17990153137222426"},{"media_type":"IMAGE","media_url":"https://scontent-lax3-1.cdninstagram.com/v/t51.2885-15/53759566_1506942669439464_1735072768369781465_n.jpg?_nc_cat=101&ccb=2&_nc_sid=8ae9d6&_nc_ohc=a9arQ1QyvMIAX8_Xnrt&_nc_ht=scontent-lax3-1.cdninstagram.com&oh=b04aba41139cc4b153651bde091ae38c&oe=5FCC6954","permalink":"https://www.instagram.com/p/BvYAu6PhEYY/","id":"17946296542268231"},{"media_type":"CAROUSEL_ALBUM","media_url":"https://scontent-lax3-1.cdninstagram.com/v/t51.2885-15/51742126_330542137571195_226618076030741819_n.jpg?_nc_cat=101&ccb=2&_nc_sid=8ae9d6&_nc_ohc=HpW2-b-gsagAX-byVbL&_nc_ht=scontent-lax3-1.cdninstagram.com&oh=9d7e1fef7167d4d75bd73c641747c761&oe=5FCD560C","permalink":"https://www.instagram.com/p/Bu2bDawBKf9/","id":"18014482024134912"},{"media_type":"CAROUSEL_ALBUM","media_url":"https://scontent-lax3-1.cdninstagram.com/v/t51.2885-15/51630242_2364420827126443_8303102701475864613_n.jpg?_nc_cat=103&ccb=2&_nc_sid=8ae9d6&_nc_ohc=X_Tq5vYCAesAX-uTcL5&_nc_ht=scontent-lax3-1.cdninstagram.com&oh=a256e74354a87a72aa77fada9a9ec47e&oe=5FCA6C26","permalink":"https://www.instagram.com/p/BumFMF_BG4T/","id":"17938960096263189"},{"media_type":"IMAGE","media_url":"https://scontent-lax3-1.cdninstagram.com/v/t51.2885-15/50713351_388798911880471_7021358772548888929_n.jpg?_nc_cat=101&ccb=2&_nc_sid=8ae9d6&_nc_ohc=AKnQhHGtedUAX_tRm90&_nc_ht=scontent-lax3-1.cdninstagram.com&oh=1113c3f4c8f05122145e4b6678ab3e55&oe=5FCC9145","permalink":"https://www.instagram.com/p/BtKdwSJH_pC/","id":"17871976990307174"},{"media_type":"CAROUSEL_ALBUM","media_url":"https://scontent-lax3-2.cdninstagram.com/v/t51.2885-15/44809009_707810086260741_4979800576931759277_n.jpg?_nc_cat=107&ccb=2&_nc_sid=8ae9d6&_nc_ohc=drmgxSSSzCoAX-H2OG2&_nc_ht=scontent-lax3-2.cdninstagram.com&oh=5beed5f278151cffc7a50dd2ac7dd5fb&oe=5FCD4466","permalink":"https://www.instagram.com/p/BqgQgPGHVX-/","id":"17973140017182392"},{"media_type":"IMAGE","media_url":"https://scontent-lax3-1.cdninstagram.com/v/t51.2885-15/42861534_110453016568268_7883323670458048778_n.jpg?_nc_cat=103&ccb=2&_nc_sid=8ae9d6&_nc_ohc=84o83zzZPJYAX-8dNat&_nc_ht=scontent-lax3-1.cdninstagram.com&oh=b5a5c696b40b8a5816b04a5366354bd5&oe=5FCD8085","permalink":"https://www.instagram.com/p/BphtdM4nvXt/","id":"17976344650123462"},{"media_type":"CAROUSEL_ALBUM","media_url":"https://scontent-lax3-1.cdninstagram.com/v/t51.2885-15/44279505_496901300812119_8367236917451904673_n.jpg?_nc_cat=102&ccb=2&_nc_sid=8ae9d6&_nc_ohc=2VdfoRYYVqoAX8Wla6Z&_nc_ht=scontent-lax3-1.cdninstagram.com&oh=e80842e1fdcd2820e30af49dbc082093&oe=5FCD0FAC","permalink":"https://www.instagram.com/p/BpPvr9ThRNc/","id":"17969550223090783"},{"media_type":"CAROUSEL_ALBUM","media_url":"https://scontent-lax3-1.cdninstagram.com/v/t51.2885-15/42002730_262100904443266_2110696001538470667_n.jpg?_nc_cat=109&ccb=2&_nc_sid=8ae9d6&_nc_ohc=YO0bD0h-Zz4AX-0m1R6&_nc_ht=scontent-lax3-1.cdninstagram.com&oh=8e8b19e3bfd119f83183c3e26b2b04dd&oe=5FCBC56D","permalink":"https://www.instagram.com/p/BoX8v4Uhx-O/","id":"17970549811097421"},{"media_type":"CAROUSEL_ALBUM","media_url":"https://scontent-lax3-1.cdninstagram.com/v/t51.2885-15/39107277_323503771735414_3573957752902385664_n.jpg?_nc_cat=103&ccb=2&_nc_sid=8ae9d6&_nc_ohc=dRNuzVRzeTsAX96qAti&_nc_ht=scontent-lax3-1.cdninstagram.com&oh=269b4b2fdb5937000fa8d4306241275c&oe=5FCC76BB","permalink":"https://www.instagram.com/p/BnFkgTrBXSj/","id":"17973883114004012"},{"media_type":"CAROUSEL_ALBUM","media_url":"https://scontent-lax3-2.cdninstagram.com/v/t51.2885-15/26870360_178649719403990_5308221570857041920_n.jpg?_nc_cat=106&ccb=2&_nc_sid=8ae9d6&_nc_ohc=93l8i0LlyHYAX9qDTBV&_nc_ht=scontent-lax3-2.cdninstagram.com&oh=7be23ed4e04a3b5ae7c359241b0fbbc3&oe=5FCBE04C","permalink":"https://www.instagram.com/p/BehXCY2ACdP/","id":"17861590261213519"},{"media_type":"CAROUSEL_ALBUM","media_url":"https://scontent-lax3-1.cdninstagram.com/v/t51.2885-15/23735420_158105054802528_3140408300751814656_n.jpg?_nc_cat=103&ccb=2&_nc_sid=8ae9d6&_nc_ohc=GXO9VB3VAVsAX_On6I1&_nc_ht=scontent-lax3-1.cdninstagram.com&oh=c491130aa3cb38acec0c56cde0d260f0&oe=5FCA43CF","permalink":"https://www.instagram.com/p/Bb3Up_yA436/","id":"17894439700120911"},{"media_type":"CAROUSEL_ALBUM","media_url":"https://scontent-lax3-2.cdninstagram.com/v/t51.2885-15/23970162_762268303974613_4669197610500751360_n.jpg?_nc_cat=106&ccb=2&_nc_sid=8ae9d6&_nc_ohc=RgrTt_qgd34AX_l8MCu&_nc_ht=scontent-lax3-2.cdninstagram.com&oh=a7d684c8b1dec54ce51171637a14c128&oe=5FCA88E7","permalink":"https://www.instagram.com/p/Bb3T6XTgoFt/","id":"17870226796199912"}]